{
  "caption": "太平洋公园，圣莫尼卡州立海滩，加利福尼亚州",
  "title": "太平洋公园，圣莫妮卡州立海滩，加利福尼亚州，美国",
  "description": "当夕阳西下，洒下橙色、粉色和紫色的光芒时，圣莫尼卡从悠闲的氛围中转为灯火通明。真的！这片海滩拥有超过3英里的沙滩、一座历史悠久的码头，以及风景如画的太平洋海岸公路，不仅仅是一条美丽的海岸线。让我们先从沙滩说起。宽阔、洁净，无论是打排球还是悠闲地读一本好书，这里都是日光浴爱好者和沙堡建造者的理想之地。",
  "copyright": "© EXTREME-PHOTOGRAPHER/Getty Images",
  "date": "2025 9月 5",
  "clickUrl": "/search?q=%e5%9c%a3%e8%8e%ab%e5%a6%ae%e5%8d%a1%e5%b7%9e%e7%ab%8b%e6%b5%b7%e6%bb%a9&form=hpcapt&filters=HpDate:\"20250904_1600\"",
  "imageUrls": {
    "landscape": {
      "highDef": "/th?id=OHR.SunsetPier_ZH-CN1202083395_1920x1080.jpg",
      "ultraHighDef": "/th?id=OHR.SunsetPier_ZH-CN1202083395_UHD.jpg",
      "wallpaper": "/th?id=OHR.SunsetPier_ZH-CN1202083395_1920x1200.jpg"
    },
    "portrait": {
      "highDef": "/th?id=OHR.SunsetPier_ZH-CN1202083395_768x1366.jpg",
      "ultraHighDef": "/th?id=OHR.SunsetPier_ZH-CN1202083395_1080x1920.jpg",
      "wallpaper": "/th?id=OHR.SunsetPier_ZH-CN1202083395_1080x1920_logo.jpg"
    }
  },
  "descriptionPara2": "然后是圣莫尼卡码头。它建于1909年，至今仍屹立于木桩之上，拥有一个名为太平洋公园的游乐园、游乐场、餐厅，以及著名的太阳能摩天轮。想体验更多运动？马文·布劳德自行车道（Marvin Braude Bike Trail），又名斯特兰德（Strand），是一条22英里长的自行车道，蜿蜒穿过海滩。租一辆自行车，骑过滑旱冰者、遛狗者，以及一边吃冰淇淋一边自拍的游客。这里的冲浪也是一大亮点。初学者可以在这里体验人生中的第一波浪潮，而专业人士则时刻关注着更远处的海浪。",
  "descriptionPara3": "",
  "isoDate": "20250905",
  "headline": "完美的夜晚",
  "quickFact": "2028年夏季奥运会期间，该海滩将举办沙滩排球和冲浪比赛。",
  "triviaId": "HPQuiz_20250905_SunsetPier",
  "triviaData": {
    "question": "圣莫尼卡于1909年建造了什么著名的特色建筑？",
    "options": [
      {
        "text": "圣莫尼卡码头",
        "url": "/search?q=%E5%9C%A3%E8%8E%AB%E5%B0%BC%E5%8D%A1%E7%A0%81%E5%A4%B4&filters=mgzv3configlist%3A%22BingQA_Quiz_Layout%22+IsConversation%3A%22True%22+btrequestsource%3A%22homepage%22+WQOskey%3A%22HPQuiz_20250905_SunsetPier%22+WQId%3A%221%22+WQQI%3A%220%22+WQCI%3A%220%22+UserChoices%3A%220%22+ShowTimesTaskPaneTrigger%3A%22false%22+WQSCORE%3A%221%22&FORM=HPQUIZ",
        "bullet": "A"
      },
      {
        "text": "太平洋海岸公路",
        "url": "/search?q=%E5%9C%A3%E8%8E%AB%E5%B0%BC%E5%8D%A1%E7%A0%81%E5%A4%B4&filters=mgzv3configlist%3A%22BingQA_Quiz_Layout%22+IsConversation%3A%22True%22+btrequestsource%3A%22homepage%22+WQOskey%3A%22HPQuiz_20250905_SunsetPier%22+WQId%3A%221%22+WQQI%3A%220%22+WQCI%3A%221%22+UserChoices%3A%221%22+ShowTimesTaskPaneTrigger%3A%22false%22+WQSCORE%3A%220%22&FORM=HPQUIZ",
        "bullet": "B"
      },
      {
        "text": "马文·布劳德自行车道",
        "url": "/search?q=%E5%9C%A3%E8%8E%AB%E5%B0%BC%E5%8D%A1%E7%A0%81%E5%A4%B4&filters=mgzv3configlist%3A%22BingQA_Quiz_Layout%22+IsConversation%3A%22True%22+btrequestsource%3A%22homepage%22+WQOskey%3A%22HPQuiz_20250905_SunsetPier%22+WQId%3A%221%22+WQQI%3A%220%22+WQCI%3A%222%22+UserChoices%3A%222%22+ShowTimesTaskPaneTrigger%3A%22false%22+WQSCORE%3A%220%22&FORM=HPQUIZ",
        "bullet": "C"
      }
    ]
  }
}