{
  "caption": "椋鸟群在布莱顿西码头废墟上空盘旋，英格兰",
  "title": "椋鸟群在布莱顿西码头废墟上空盘旋, 英格兰",
  "description": "椋鸟是天生的“舞台明星”，它们深谙抢镜之道：羽毛在阳光下闪烁绿紫光泽，叫声里还夹杂着模仿的趣味。椋鸟原产于欧亚大陆，如今已遍布全球。19世纪，一位痴迷莎士比亚作品的鸟类爱好者，将椋鸟引入纽约中央公园，从此开启了它们的美洲传奇。",
  "copyright": "© Philip Reeve/Photodisc/Getty Images",
  "date": "2026 1月 8",
  "clickUrl": "/search?q=%e6%a4%8b%e9%b8%9f&form=hpcapt&filters=HpDate:\"20260107_1600\"",
  "imageUrls": {
    "landscape": {
      "highDef": "/th?id=OHR.StarlingBrighton2025_ZH-CN2775446092_1920x1080.jpg",
      "ultraHighDef": "/th?id=OHR.StarlingBrighton2025_ZH-CN2775446092_UHD.jpg",
      "wallpaper": "/th?id=OHR.StarlingBrighton2025_ZH-CN2775446092_1920x1200.jpg"
    },
    "portrait": {
      "highDef": "/th?id=OHR.StarlingBrighton2025_ZH-CN2775446092_768x1366.jpg",
      "ultraHighDef": "/th?id=OHR.StarlingBrighton2025_ZH-CN2775446092_1080x1920.jpg",
      "wallpaper": "/th?id=OHR.StarlingBrighton2025_ZH-CN2775446092_1080x1920_logo.jpg"
    }
  },
  "descriptionPara2": "英格兰布莱顿西码头，锈迹斑驳，却在椋鸟云潮掠过时焕发生机。每逢秋冬黄昏，成千上万的椋鸟在空中翻涌，宛如一曲无声的交响乐。这场奇景被称作“椋鸟群舞”，名字本身就带着韵律感，恰似翅膀拍击的节奏。科学家认为，鸟群俯冲盘旋是为了迷惑天敌、保持体温，并传递栖息地的信息。无论缘由如何，这场天幕之舞总令游客举起手机仰望，在鸟群归巢前争相捕捉这转瞬即逝的奇观。",
  "descriptionPara3": "",
  "isoDate": "20260108",
  "headline": "废墟之上，椋鸟群舞",
  "quickFact": "椋鸟的鸣声丰富而复杂，它们甚至会把周围的声音融入自己的叫声，从汽车警报到人类的语音节奏，无所不包。更令人惊讶的是，它们能凭叫声辨认特定的同伴。这种能力，使椋鸟成为科学家探索语言起源的重要线索。",
  "triviaId": "HPQuiz_20260108_StarlingBrighton2025",
  "triviaData": {
    "question": "椋鸟羽毛的显著特征是什么？",
    "options": [
      {
        "text": "绿色与紫色光泽",
        "url": "/search?q=%E7%BB%BF%E8%89%B2%E4%B8%8E%E7%B4%AB%E8%89%B2%E5%85%89%E6%B3%BD&filters=mgzv3configlist%3A%22BingQA_Quiz_layout%22+IsConversation%3A%22True%22+btrequestsource%3A%22homepage%22+WQOskey%3A%22HPQuiz_20260108_StarlingBrighton2025%22+WQId%3A%221%22+WQQI%3A%220%22+WQCI%3A%220%22+UserChoices%3A%220%22+ShowTimesTaskPaneTrigger%3A%22false%22+WQSCORE%3A%221%22&FORM=HPQUIZ",
        "bullet": "A"
      },
      {
        "text": "明亮的黄色",
        "url": "/search?q=%E7%BB%BF%E8%89%B2%E4%B8%8E%E7%B4%AB%E8%89%B2%E5%85%89%E6%B3%BD&filters=mgzv3configlist%3A%22BingQA_Quiz_layout%22+IsConversation%3A%22True%22+btrequestsource%3A%22homepage%22+WQOskey%3A%22HPQuiz_20260108_StarlingBrighton2025%22+WQId%3A%221%22+WQQI%3A%220%22+WQCI%3A%221%22+UserChoices%3A%221%22+ShowTimesTaskPaneTrigger%3A%22false%22+WQSCORE%3A%220%22&FORM=HPQUIZ",
        "bullet": "B"
      },
      {
        "text": "斑点图案",
        "url": "/search?q=%E7%BB%BF%E8%89%B2%E4%B8%8E%E7%B4%AB%E8%89%B2%E5%85%89%E6%B3%BD&filters=mgzv3configlist%3A%22BingQA_Quiz_layout%22+IsConversation%3A%22True%22+btrequestsource%3A%22homepage%22+WQOskey%3A%22HPQuiz_20260108_StarlingBrighton2025%22+WQId%3A%221%22+WQQI%3A%220%22+WQCI%3A%222%22+UserChoices%3A%222%22+ShowTimesTaskPaneTrigger%3A%22false%22+WQSCORE%3A%220%22&FORM=HPQUIZ",
        "bullet": "C"
      }
    ]
  }
}